README.txt
setup.py
MasTurboZpt.egg-info/PKG-INFO
MasTurboZpt.egg-info/SOURCES.txt
MasTurboZpt.egg-info/dependency_links.txt
MasTurboZpt.egg-info/entry_points.txt
MasTurboZpt.egg-info/not-zip-safe
MasTurboZpt.egg-info/requires.txt
MasTurboZpt.egg-info/top_level.txt
ez_setup/__init__.py
masturbozpt/__init__.py
masturbozpt/template.py
masturbozpt/zptsupport.py
