Metadata-Version: 1.0
Name: MasTurboZpt
Version: 0.1.4
Summary: Pylons plugin to support use of Zope Page Templates
Home-page: UNKNOWN
Author: RAdmin Crew
Author-email: radmin@autistici.org
License: MIT
Platform: UNKNOWN
Classifier: Development Status :: 3 - Alpha
Classifier: Operating System :: OS Independent
Classifier: Programming Language :: Python
Classifier: License :: OSI Approved :: MIT License
Classifier: Topic :: Software Development :: Libraries :: Python Modules
